alignn/__init__.py
alignn/cli.py
alignn/config.py
alignn/config.yaml
alignn/data.py
alignn/graphs.py
alignn/pretrained.py
alignn/profile.py
alignn/run_alignn_ff.py
alignn/train.py
alignn/train_folder.py
alignn/train_folder_ff.py
alignn/train_props.py
alignn/utils.py
alignn/examples/sample_data/POSCAR-JVASP-10.vasp
alignn/ff/__init__.py
alignn/ff/ff.py
alignn/models/__init__.py
alignn/models/alignn.py
alignn/models/alignn_atomwise.py
alignn/models/alignn_cgcnn.py
alignn/models/alignn_layernorm.py
alignn/models/dense_alignn.py
alignn/models/densegcn.py
alignn/models/gcn.py
alignn/models/icgcnn.py
alignn/models/modified_cgcnn.py
alignn/models/utils.py
alignn/scripts/__init__.py
alignn/scripts/alignn_evac.py
alignn/scripts/all_train_cgcnn.py
alignn/scripts/compare_cfid.py
alignn/scripts/cubic_mat_relax.py
alignn/scripts/data_1.json
alignn/scripts/dataset_props.json
alignn/scripts/defect.py
alignn/scripts/early_stopping_checker.py
alignn/scripts/ev_curve.py
alignn/scripts/ev_curve_comp.py
alignn/scripts/final_model.py
alignn/scripts/graph_viz.py
alignn/scripts/make_test_split_cross_pred.py
alignn/scripts/plot_ff_results.py
alignn/scripts/plot_phonons_ff.py
alignn/scripts/predict.py
alignn/scripts/predict_db.py
alignn/scripts/predict_db_all.py
alignn/scripts/train_all_hmof.py
alignn/scripts/train_all_hpov.py
alignn/scripts/train_all_jv.py
alignn/scripts/train_all_jv_class.py
alignn/scripts/train_all_jv_dal.py
alignn/scripts/train_all_mp.py
alignn/scripts/train_all_oqmd.py
alignn/scripts/train_all_pdbbind.py
alignn/scripts/train_all_qetb.py
alignn/scripts/train_all_qm9_jctc.py
alignn/scripts/train_all_qmof.py
alignn/scripts/train_cgcnn_repo.py
alignn/scripts/train_edos_pdos.py
alignn/scripts/train_megnet.py
alignn/tests/test_alignn_ff.py
alignn/tests/test_force_reduction.py
alignn/tests/test_prop.py
mpdd_alignn-1.2.0.dist-info/licenses/LICENSE.md
mpdd_alignn-1.2.0.dist-info/METADATA
mpdd_alignn-1.2.0.dist-info/WHEEL
mpdd_alignn-1.2.0.dist-info/top_level.txt
mpdd_alignn-1.2.0.dist-info/RECORD
