Metadata-Version: 2.4
Name: mpdd-alignn
Version: 1.2.0
Summary: Our version of the NIST-JARVIS ALIGNN optimized in terms of model performance and to some extent reliability, for large-scale deployments over the MPDD infrastructure by Phases Research Lab.
Author-email: "Adam M. Krajewski" <adam@phaseslab.org>
Project-URL: Homepage, https://github.com/PhasesResearchLab/mpdd-alignn
Project-URL: Bug Tracker, https://github.com/PhasesResearchLab/mpdd-alignn/issues
Project-URL: Research Page, https://phaseslab.com/mpdd
Project-URL: MPDD OPTIMADE Access, https://optimade.mpdd.org
Project-URL: MPDD Simple GUI, http://mpdd.org
Project-URL: ALIGNN, https://github.com/usnistgov/alignn
Classifier: Programming Language :: Python :: 3
Classifier: Programming Language :: Python :: 3.9
Classifier: Programming Language :: Python :: 3.10
Classifier: Programming Language :: Python :: 3.11
Classifier: Development Status :: 4 - Beta
Classifier: Intended Audience :: Science/Research
Classifier: License :: OSI Approved :: MIT License
Classifier: Operating System :: OS Independent
Classifier: Topic :: Scientific/Engineering
Classifier: Topic :: Scientific/Engineering :: Artificial Intelligence
Classifier: Topic :: Scientific/Engineering :: Chemistry
Classifier: Topic :: Scientific/Engineering :: Physics
Requires-Python: >=3.9
License-File: LICENSE.md
Requires-Dist: spglib==2.0.2
Requires-Dist: numpy<2.0.0,>=1.26.0
Requires-Dist: scipy>=1.11.0
Requires-Dist: jarvis-tools>=2021.07.19
Requires-Dist: torch>=2.1.0
Requires-Dist: torchdata==0.9.0
Requires-Dist: dgl>=1.1.3
Requires-Dist: scikit-learn>=1.3.1
Requires-Dist: matplotlib>=3.4.1
Requires-Dist: tqdm>=4.60.0
Requires-Dist: pandas>=1.2.3
Requires-Dist: pydantic_settings
Requires-Dist: ruamel.yaml
Requires-Dist: pysmartdl2
Provides-Extra: full
Requires-Dist: pytorch-ignite>=0.5.0.dev20221024; extra == "full"
Requires-Dist: ase; extra == "full"
Requires-Dist: flake8>=3.9.1; extra == "full"
Requires-Dist: pycodestyle>=2.7.0; extra == "full"
Requires-Dist: pydocstyle>=6.0.0; extra == "full"
Requires-Dist: pyparsing<3,>=2.2.1; extra == "full"
Requires-Dist: accelerate>=0.20.3; extra == "full"
Dynamic: license-file
